{
  "name": "gen-162",
  "viewport": 768,
  "chromium": "148.0.7778.96",
  "generatedAt": "2026-06-11T22:46:47.462Z",
  "rects": {
    "r": {
      "x": 0,
      "y": 0,
      "width": 768,
      "height": 675
    },
    "r.0": {
      "x": 0,
      "y": 0,
      "width": 768,
      "height": 52
    },
    "r.1": {
      "x": 0,
      "y": 52,
      "width": 768,
      "height": 392
    },
    "r.1.0": {
      "x": 12,
      "y": 64,
      "width": 266,
      "height": 105
    },
    "r.1.1": {
      "x": 12,
      "y": 193,
      "width": 744,
      "height": 24
    },
    "r.1.2": {
      "x": 12,
      "y": 241,
      "width": 178,
      "height": 59
    },
    "r.1.3": {
      "x": 12,
      "y": 324,
      "width": 744,
      "height": 108
    },
    "r.1.3.0": {
      "x": 28,
      "y": 340,
      "width": 39,
      "height": 34
    },
    "r.1.3.1": {
      "x": 67,
      "y": 340,
      "width": 175,
      "height": 76
    },
    "r.1.3.2": {
      "x": 242,
      "y": 340,
      "width": 370,
      "height": 13
    },
    "r.1.3.3": {
      "x": 612,
      "y": 340,
      "width": 128,
      "height": 37
    },
    "r.2": {
      "x": 0,
      "y": 444,
      "width": 768,
      "height": 28
    },
    "r.3": {
      "x": 0,
      "y": 472,
      "width": 768,
      "height": 203
    },
    "r.3.0": {
      "x": 8,
      "y": 480,
      "width": 0,
      "height": 76
    },
    "r.3.1": {
      "x": 12,
      "y": 480,
      "width": 431.75,
      "height": 187
    },
    "r.3.1.0": {
      "x": 12,
      "y": 480,
      "width": 431.75,
      "height": 48
    },
    "r.3.1.1": {
      "x": 188.38,
      "y": 552,
      "width": 79,
      "height": 115
    },
    "r.3.1.2": {
      "x": 390.75,
      "y": 481,
      "width": 41,
      "height": 35
    },
    "r.3.2": {
      "x": 447.75,
      "y": 480,
      "width": 144.45,
      "height": 103
    },
    "r.3.3": {
      "x": 596.2,
      "y": 480,
      "width": 163.8,
      "height": 187
    }
  }
}
