{
  "name": "tw-product-card",
  "viewport": 320,
  "chromium": "148.0.7778.96",
  "generatedAt": "2026-06-11T12:41:19.425Z",
  "rects": {
    "r": {
      "x": 0,
      "y": 0,
      "width": 320,
      "height": 374.88
    },
    "r.0": {
      "x": 16,
      "y": 16,
      "width": 288,
      "height": 342.88
    },
    "r.0.0": {
      "x": 17,
      "y": 17,
      "width": 286,
      "height": 160.88
    },
    "r.0.1": {
      "x": 17,
      "y": 177.88,
      "width": 286,
      "height": 180
    },
    "r.0.1.0": {
      "x": 33,
      "y": 193.88,
      "width": 254,
      "height": 48
    },
    "r.0.1.0.0": {
      "x": 33,
      "y": 193.88,
      "width": 207.41,
      "height": 48
    },
    "r.0.1.0.1": {
      "x": 248.41,
      "y": 193.88,
      "width": 38.59,
      "height": 24
    },
    "r.0.1.1": {
      "x": 33,
      "y": 249.88,
      "width": 254,
      "height": 40
    },
    "r.0.1.2": {
      "x": 33,
      "y": 305.88,
      "width": 254,
      "height": 36
    }
  }
}
